{
  "info": {
    "_postman_id": "02b8d031-38a7-40ce-ba4e-d3bde87b4f54",
    "name": "DummyJSON_API_Testing",
    "schema": "https://schema.getpostman.com/json/collection/v2.1.0/collection.json",
    "_exporter_id": "44197007",
    "_collection_link": "https://go.postman.co/collection/44197007-02b8d031-38a7-40ce-ba4e-d3bde87b4f54?source=collection_link"
  },
  "item": [
    {
      "name": "auth",
      "item": [
        {
          "name": "Login",
          "event": [
            {
              "listen": "test",
              "script": {
                "exec": [
                  "pm.test(\"Login success status\", function () {",
                  "    pm.response.to.have.status(200);",
                  "});",
                  "",
                  "pm.test(\"Response time OK\", function () {",
                  "    pm.expect(pm.response.responseTime).to.be.below(2000);",
                  "});",
                  "",
                  "pm.environment.set(\"token\", pm.response.json().accessToken);",
                  ""
                ],
                "type": "text/javascript",
                "packages": {},
                "requests": {}
              }
            }
          ],
          "request": {
            "method": "POST",
            "header": [],
            "body": {
              "mode": "raw",
              "raw": "{\n  \"username\": \"emilys\",\n  \"password\": \"emilyspass\"\n}\n",
              "options": {
                "raw": {
                  "language": "json"
                }
              }
            },
            "url": {
              "raw": "{{baseUrl}}/auth/login",
              "host": [
                "{{baseUrl}}"
              ],
              "path": [
                "auth",
                "login"
              ]
            }
          },
          "response": []
        },
        {
          "name": "Login (invalid input)",
          "event": [
            {
              "listen": "test",
              "script": {
                "exec": [
                  "pm.test(\"Invalid login returns error\", function () {",
                  "    pm.expect(pm.response.code).to.be.oneOf([400,401]);",
                  "});",
                  "",
                  "pm.test(\"Error message exists\", function () {",
                  "    pm.expect(pm.response.text()).to.not.be.empty;",
                  "});",
                  "pm.environment.set(\"token\", pm.response.json().accessToken);",
                  ""
                ],
                "type": "text/javascript",
                "packages": {},
                "requests": {}
              }
            }
          ],
          "request": {
            "method": "POST",
            "header": [],
            "body": {
              "mode": "raw",
              "raw": "{\n  \"username\": \"maitaha\",\n  \"password\": \"emilyspass\"\n}\n",
              "options": {
                "raw": {
                  "language": "json"
                }
              }
            },
            "url": {
              "raw": "{{baseUrl}}/auth/login",
              "host": [
                "{{baseUrl}}"
              ],
              "path": [
                "auth",
                "login"
              ]
            }
          },
          "response": []
        }
      ]
    },
    {
      "name": "products",
      "item": [
        {
          "name": "Get Products",
          "event": [
            {
              "listen": "test",
              "script": {
                "exec": [
                  "pm.test(\"Status 200\", () => { pm.response.to.have.status(200);});",
                  "",
                  "pm.test(\"Products returned\", () => {pm.expect(pm.response.json()).to.have.property(\"products\");});",
                  "",
                  "pm.test(\"Response time OK\", () => {pm.expect(pm.response.responseTime).to.be.below(2000);});",
                  "pm.test(\"Response schema is valid\", function () {const jsonData = pm.response.json();",
                  "    pm.expect(jsonData).to.have.property(\"products\");",
                  "    pm.expect(jsonData.products).to.be.an(\"array\");",
                  "});",
                  ""
                ],
                "type": "text/javascript",
                "packages": {},
                "requests": {}
              }
            }
          ],
          "protocolProfileBehavior": {
            "disableBodyPruning": true
          },
          "request": {
            "auth": {
              "type": "bearer",
              "bearer": [
                {
                  "key": "token",
                  "value": "{{token}}",
                  "type": "string"
                }
              ]
            },
            "method": "GET",
            "header": [],
            "body": {
              "mode": "raw",
              "raw": "",
              "options": {
                "raw": {
                  "language": "json"
                }
              }
            },
            "url": {
              "raw": "{{baseUrl}}/products",
              "host": [
                "{{baseUrl}}"
              ],
              "path": [
                "products"
              ]
            }
          },
          "response": []
        },
        {
          "name": "Get Products (limits)",
          "event": [
            {
              "listen": "test",
              "script": {
                "exec": [
                  "pm.test(\"Status 200\", () => {",
                  "    pm.response.to.have.status(200);",
                  "});",
                  "",
                  "pm.test(\"Products returned\", () => {",
                  "    pm.expect(pm.response.json()).to.have.property(\"products\");",
                  "});",
                  "",
                  "pm.test(\"Response time OK\", () => {",
                  "    pm.expect(pm.response.responseTime).to.be.below(2000);",
                  "});",
                  ""
                ],
                "type": "text/javascript",
                "packages": {},
                "requests": {}
              }
            }
          ],
          "request": {
            "auth": {
              "type": "bearer",
              "bearer": [
                {
                  "key": "token",
                  "value": "{{token}}",
                  "type": "string"
                }
              ]
            },
            "method": "GET",
            "header": [],
            "url": {
              "raw": "{{baseUrl}}/products?limit=5",
              "host": [
                "{{baseUrl}}"
              ],
              "path": [
                "products"
              ],
              "query": [
                {
                  "key": "limit",
                  "value": "5"
                }
              ]
            }
          },
          "response": []
        },
        {
          "name": "Get Products (skip)",
          "event": [
            {
              "listen": "test",
              "script": {
                "exec": [
                  "pm.test(\"Status 200\", () => {",
                  "    pm.response.to.have.status(200);",
                  "});",
                  "",
                  "pm.test(\"Products returned\", () => {",
                  "    pm.expect(pm.response.json()).to.have.property(\"products\");",
                  "});",
                  "",
                  "pm.test(\"Response time OK\", () => {",
                  "    pm.expect(pm.response.responseTime).to.be.below(2000);",
                  "});",
                  ""
                ],
                "type": "text/javascript",
                "packages": {},
                "requests": {}
              }
            }
          ],
          "request": {
            "auth": {
              "type": "bearer",
              "bearer": [
                {
                  "key": "token",
                  "value": "{{token}}",
                  "type": "string"
                }
              ]
            },
            "method": "GET",
            "header": [],
            "url": {
              "raw": "{{baseUrl}}/products?skip=10",
              "host": [
                "{{baseUrl}}"
              ],
              "path": [
                "products"
              ],
              "query": [
                {
                  "key": "skip",
                  "value": "10"
                }
              ]
            }
          },
          "response": []
        },
        {
          "name": "Get Product by id",
          "event": [
            {
              "listen": "test",
              "script": {
                "exec": [
                  "pm.test(\"Status 200\", () => {",
                  "    pm.response.to.have.status(200);",
                  "});",
                  "",
                  "pm.test(\"Response time OK\", () => {",
                  "    pm.expect(pm.response.responseTime).to.be.below(2000);",
                  "});",
                  ""
                ],
                "type": "text/javascript",
                "packages": {},
                "requests": {}
              }
            }
          ],
          "protocolProfileBehavior": {
            "disableBodyPruning": true
          },
          "request": {
            "auth": {
              "type": "bearer",
              "bearer": [
                {
                  "key": "token",
                  "value": "{{token}}",
                  "type": "string"
                }
              ]
            },
            "method": "GET",
            "header": [],
            "body": {
              "mode": "raw",
              "raw": "",
              "options": {
                "raw": {
                  "language": "json"
                }
              }
            },
            "url": {
              "raw": "{{baseUrl}}/products/10",
              "host": [
                "{{baseUrl}}"
              ],
              "path": [
                "products",
                "10"
              ]
            }
          },
          "response": []
        },
        {
          "name": "Get Product by id (Invalid input)",
          "event": [
            {
              "listen": "test",
              "script": {
                "exec": [
                  "pm.test(\"Invalid product id handled\",() => {",
                  "    pm.response.to.have.status(404);",
                  "});",
                  "pm.test(\"Error or empty result\", function () {",
                  "    pm.expect(pm.response.text()).to.not.be.empty;",
                  "});",
                  ""
                ],
                "type": "text/javascript",
                "packages": {},
                "requests": {}
              }
            }
          ],
          "request": {
            "auth": {
              "type": "bearer",
              "bearer": [
                {
                  "key": "token",
                  "value": "{{token}}",
                  "type": "string"
                }
              ]
            },
            "method": "GET",
            "header": [],
            "url": {
              "raw": "{{baseUrl}}/products/1234",
              "host": [
                "{{baseUrl}}"
              ],
              "path": [
                "products",
                "1234"
              ]
            }
          },
          "response": []
        },
        {
          "name": "Get Product Categories",
          "event": [
            {
              "listen": "test",
              "script": {
                "exec": [
                  "pm.test(\"Status 200\", () => {",
                  "    pm.response.to.have.status(200);",
                  "});",
                  "",
                  "pm.test(\"Response time OK\", () => {",
                  "    pm.expect(pm.response.responseTime).to.be.below(2000);",
                  "});",
                  ""
                ],
                "type": "text/javascript",
                "packages": {},
                "requests": {}
              }
            }
          ],
          "request": {
            "auth": {
              "type": "bearer",
              "bearer": [
                {
                  "key": "token",
                  "value": "{{token}}",
                  "type": "string"
                }
              ]
            },
            "method": "GET",
            "header": [],
            "url": {
              "raw": "{{baseUrl}}/products/categories",
              "host": [
                "{{baseUrl}}"
              ],
              "path": [
                "products",
                "categories"
              ]
            }
          },
          "response": []
        },
        {
          "name": "Get Product by Category",
          "event": [
            {
              "listen": "test",
              "script": {
                "exec": [
                  "pm.test(\"Status 200\", () => {",
                  "    pm.response.to.have.status(200);",
                  "});",
                  "",
                  "pm.test(\"Products returned\", () => {",
                  "    pm.expect(pm.response.json()).to.have.property(\"products\");",
                  "});",
                  "",
                  "pm.test(\"Response time OK\", () => {",
                  "    pm.expect(pm.response.responseTime).to.be.below(2000);",
                  "});",
                  ""
                ],
                "type": "text/javascript",
                "packages": {},
                "requests": {}
              }
            }
          ],
          "request": {
            "auth": {
              "type": "bearer",
              "bearer": [
                {
                  "key": "token",
                  "value": "{{token}}",
                  "type": "string"
                }
              ]
            },
            "method": "GET",
            "header": [],
            "url": {
              "raw": "{{baseUrl}}/products/category/beauty",
              "host": [
                "{{baseUrl}}"
              ],
              "path": [
                "products",
                "category",
                "beauty"
              ]
            }
          },
          "response": []
        },
        {
          "name": "Add Product (csv file)",
          "event": [
            {
              "listen": "test",
              "script": {
                "exec": [
                  "var expectedStatus = parseInt(pm.iterationData.get(\"expectedStatus\"));",
                  "var testCaseName = pm.iterationData.get(\"testCase\");",
                  "",
                  "pm.test(\"Status code is \" + expectedStatus + \" for case: \" + testCaseName, function () {",
                  "    pm.response.to.have.status(expectedStatus);",
                  "});"
                ],
                "type": "text/javascript",
                "packages": {},
                "requests": {}
              }
            }
          ],
          "request": {
            "auth": {
              "type": "bearer",
              "bearer": [
                {
                  "key": "token",
                  "value": "{{token}}",
                  "type": "string"
                }
              ]
            },
            "method": "POST",
            "header": [],
            "body": {
              "mode": "raw",
              "raw": "{\n  \"title\": \"Test Product \",\n  \"price\": {{price}}\n}\n",
              "options": {
                "raw": {
                  "language": "json"
                }
              }
            },
            "url": {
              "raw": "{{baseUrl}}/products/add",
              "host": [
                "{{baseUrl}}"
              ],
              "path": [
                "products",
                "add"
              ]
            }
          },
          "response": []
        },
        {
          "name": "Add Product",
          "event": [
            {
              "listen": "test",
              "script": {
                "exec": [
                  "pm.test(\"Product added\", () => {",
                  "    pm.response.to.have.status(201);",
                  "});",
                  "",
                  "pm.test(\"Product id exists\", () => {",
                  "    pm.expect(pm.response.json().id).to.exist;",
                  "});",
                  "",
                  "pm.test(\"Title exists\", () => {",
                  "    pm.expect(pm.response.json()).to.have.property(\"title\");",
                  "});",
                  "",
                  "pm.environment.set(\"productId\", pm.response.json().id);",
                  ""
                ],
                "type": "text/javascript",
                "packages": {},
                "requests": {}
              }
            }
          ],
          "request": {
            "auth": {
              "type": "bearer",
              "bearer": [
                {
                  "key": "token",
                  "value": "{{token}}",
                  "type": "string"
                }
              ]
            },
            "method": "POST",
            "header": [],
            "body": {
              "mode": "raw",
              "raw": "{\n  \"title\": \"Mai Test Product \",\n  \"price\": 100,\n  \"description\": \"Added Product For API Testing  \",\n  \"category\": \"laptops\"\n\n}\n",
              "options": {
                "raw": {
                  "language": "json"
                }
              }
            },
            "url": {
              "raw": "{{baseUrl}}/products/add",
              "host": [
                "{{baseUrl}}"
              ],
              "path": [
                "products",
                "add"
              ]
            }
          },
          "response": []
        },
        {
          "name": "patch Product",
          "event": [
            {
              "listen": "test",
              "script": {
                "exec": [
                  "pm.test(\"Update success\", () => {",
                  "    pm.response.to.have.status(200);",
                  "});",
                  "",
                  "pm.test(\"Updated fields returned\", () => {",
                  "    pm.expect(pm.response.text()).to.not.be.empty;",
                  "});",
                  ""
                ],
                "type": "text/javascript",
                "packages": {},
                "requests": {}
              }
            }
          ],
          "request": {
            "auth": {
              "type": "bearer",
              "bearer": [
                {
                  "key": "token",
                  "value": "{{token}}",
                  "type": "string"
                }
              ]
            },
            "method": "PATCH",
            "header": [],
            "body": {
              "mode": "raw",
              "raw": "{\n  \"price\": 555\n}\n",
              "options": {
                "raw": {
                  "language": "json"
                }
              }
            },
            "url": {
              "raw": "{{baseUrl}}/products/1",
              "host": [
                "{{baseUrl}}"
              ],
              "path": [
                "products",
                "1"
              ]
            }
          },
          "response": []
        },
        {
          "name": "Update Product",
          "event": [
            {
              "listen": "test",
              "script": {
                "exec": [
                  "pm.test(\"Update success\", () => {",
                  "    pm.response.to.have.status(200);",
                  "});",
                  "",
                  "pm.test(\"Updated fields returned\", () => {",
                  "    pm.expect(pm.response.text()).to.not.be.empty;",
                  "});",
                  ""
                ],
                "type": "text/javascript",
                "packages": {},
                "requests": {}
              }
            }
          ],
          "request": {
            "auth": {
              "type": "bearer",
              "bearer": [
                {
                  "key": "token",
                  "value": "{{token}}",
                  "type": "string"
                }
              ]
            },
            "method": "PUT",
            "header": [],
            "body": {
              "mode": "raw",
              "raw": "{\n  \"title\": \"Updated Test Product\",\n  \"price\": 300\n}\n",
              "options": {
                "raw": {
                  "language": "json"
                }
              }
            },
            "url": {
              "raw": "{{baseUrl}}/products/2",
              "host": [
                "{{baseUrl}}"
              ],
              "path": [
                "products",
                "2"
              ]
            }
          },
          "response": []
        },
        {
          "name": "Update Product (invalid input)",
          "event": [
            {
              "listen": "test",
              "script": {
                "exec": [
                  "pm.test(\"Invalid update handled\",() => {",
                  "    pm.response.to.have.status(404);",
                  "});"
                ],
                "type": "text/javascript",
                "packages": {},
                "requests": {}
              }
            }
          ],
          "request": {
            "auth": {
              "type": "bearer",
              "bearer": [
                {
                  "key": "token",
                  "value": "{{token}}",
                  "type": "string"
                }
              ]
            },
            "method": "PUT",
            "header": [],
            "body": {
              "mode": "raw",
              "raw": "{\n  \"title\": \"Updated Test Product\",\n  \"price\": 300\n}\n",
              "options": {
                "raw": {
                  "language": "json"
                }
              }
            },
            "url": {
              "raw": "{{baseUrl}}/products/678",
              "host": [
                "{{baseUrl}}"
              ],
              "path": [
                "products",
                "678"
              ]
            }
          },
          "response": []
        },
        {
          "name": "Delete Product",
          "event": [
            {
              "listen": "test",
              "script": {
                "exec": [
                  "pm.test(\"Delete success\", () => {",
                  "    pm.response.to.have.status(200);",
                  "});",
                  "",
                  "pm.test(\"Delete response returned\", () => {",
                  "    pm.expect(pm.response.text()).to.not.be.empty;",
                  "});",
                  ""
                ],
                "type": "text/javascript",
                "packages": {},
                "requests": {}
              }
            }
          ],
          "request": {
            "auth": {
              "type": "bearer",
              "bearer": [
                {
                  "key": "token",
                  "value": "{{token}}",
                  "type": "string"
                }
              ]
            },
            "method": "DELETE",
            "header": [],
            "url": {
              "raw": "{{baseUrl}}/products/1",
              "host": [
                "{{baseUrl}}"
              ],
              "path": [
                "products",
                "1"
              ]
            }
          },
          "response": []
        },
        {
          "name": "Delete Product (Invalid input)",
          "event": [
            {
              "listen": "test",
              "script": {
                "exec": [
                  "pm.test(\"Invalid delete handled\",() => {",
                  "    pm.response.to.have.status(404);",
                  "});"
                ],
                "type": "text/javascript",
                "packages": {},
                "requests": {}
              }
            }
          ],
          "request": {
            "method": "DELETE",
            "header": [],
            "url": {
              "raw": "{{baseUrl}}/products/99999",
              "host": [
                "{{baseUrl}}"
              ],
              "path": [
                "products",
                "99999"
              ]
            }
          },
          "response": []
        },
        {
          "name": "Search Products",
          "event": [
            {
              "listen": "test",
              "script": {
                "exec": [
                  "pm.test(\"Status 200\", () => {",
                  "    pm.response.to.have.status(200);",
                  "});",
                  "",
                  "pm.test(\"Products returned\", () => {",
                  "    pm.expect(pm.response.json()).to.have.property(\"products\");",
                  "});",
                  "",
                  "pm.test(\"Response time OK\", () => {",
                  "    pm.expect(pm.response.responseTime).to.be.below(2000);",
                  "});",
                  ""
                ],
                "type": "text/javascript",
                "packages": {},
                "requests": {}
              }
            }
          ],
          "request": {
            "auth": {
              "type": "bearer",
              "bearer": [
                {
                  "key": "token",
                  "value": "{{token}}",
                  "type": "string"
                }
              ]
            },
            "method": "GET",
            "header": [],
            "url": {
              "raw": "{{baseUrl}}/products/search?q=phone",
              "host": [
                "{{baseUrl}}"
              ],
              "path": [
                "products",
                "search"
              ],
              "query": [
                {
                  "key": "q",
                  "value": "phone"
                }
              ]
            }
          },
          "response": []
        },
        {
          "name": "Search Products (Invalid input)",
          "event": [
            {
              "listen": "test",
              "script": {
                "exec": [
                  "pm.test(\"Invalid search handled\",() => {",
                  "    pm.response.to.have.status(200);",
                  "});"
                ],
                "type": "text/javascript",
                "packages": {},
                "requests": {}
              }
            }
          ],
          "protocolProfileBehavior": {
            "disableBodyPruning": true
          },
          "request": {
            "auth": {
              "type": "bearer",
              "bearer": [
                {
                  "key": "token",
                  "value": "{{token}}",
                  "type": "string"
                }
              ]
            },
            "method": "GET",
            "header": [],
            "body": {
              "mode": "raw",
              "raw": "",
              "options": {
                "raw": {
                  "language": "json"
                }
              }
            },
            "url": {
              "raw": "{{baseUrl}}/products/search?q=zzzzzzz",
              "host": [
                "{{baseUrl}}"
              ],
              "path": [
                "products",
                "search"
              ],
              "query": [
                {
                  "key": "q",
                  "value": "zzzzzzz"
                }
              ]
            }
          },
          "response": []
        },
        {
          "name": "Get Users",
          "event": [
            {
              "listen": "test",
              "script": {
                "exec": [
                  "pm.test(\"Status 200\", function () {",
                  "    pm.response.to.have.status(200);",
                  "});",
                  "",
                  "pm.test(\"Users returned\", function () {",
                  "    pm.expect(pm.response.text()).to.not.be.empty;",
                  "});",
                  "",
                  "pm.test(\"Response time OK\", function () {",
                  "    pm.expect(pm.response.responseTime).to.be.below(2000);",
                  "});",
                  ""
                ],
                "type": "text/javascript",
                "packages": {},
                "requests": {}
              }
            }
          ],
          "request": {
            "auth": {
              "type": "bearer",
              "bearer": [
                {
                  "key": "token",
                  "value": "{{token}}",
                  "type": "string"
                }
              ]
            },
            "method": "GET",
            "header": [],
            "url": {
              "raw": "{{baseUrl}}/users",
              "host": [
                "{{baseUrl}}"
              ],
              "path": [
                "users"
              ]
            }
          },
          "response": []
        }
      ]
    },
    {
      "name": "cart",
      "item": [
        {
          "name": "Get cart",
          "event": [
            {
              "listen": "test",
              "script": {
                "exec": [
                  "pm.test(\"Cart fetched\", () => {",
                  "    pm.response.to.have.status(200);",
                  "});",
                  "",
                  "pm.test(\"Cart data exists\", () => {",
                  "    pm.expect(pm.response.text()).to.not.be.empty;",
                  "});",
                  ""
                ],
                "type": "text/javascript",
                "packages": {},
                "requests": {}
              }
            }
          ],
          "request": {
            "auth": {
              "type": "bearer",
              "bearer": [
                {
                  "key": "token",
                  "value": "{{token}}",
                  "type": "string"
                }
              ]
            },
            "method": "GET",
            "header": [],
            "url": {
              "raw": "{{baseUrl}}/carts",
              "host": [
                "{{baseUrl}}"
              ],
              "path": [
                "carts"
              ]
            }
          },
          "response": []
        },
        {
          "name": "Add cart",
          "event": [
            {
              "listen": "test",
              "script": {
                "exec": [
                  "pm.test(\"Cart added\", () => {",
                  "    pm.response.to.have.status(201);",
                  "});",
                  "",
                  "pm.test(\"Cart id exists\", () => {",
                  "    pm.expect(pm.response.json().id).to.exist;",
                  "});",
                  ""
                ],
                "type": "text/javascript",
                "packages": {},
                "requests": {}
              }
            }
          ],
          "request": {
            "auth": {
              "type": "bearer",
              "bearer": [
                {
                  "key": "token",
                  "value": "{{token}}",
                  "type": "string"
                }
              ]
            },
            "method": "POST",
            "header": [],
            "body": {
              "mode": "raw",
              "raw": "{\n  \"userId\": 1,\n  \"products\": [\n    {\n      \"id\": 1,\n      \"quantity\": 2\n    }\n  ]\n}\n",
              "options": {
                "raw": {
                  "language": "json"
                }
              }
            },
            "url": {
              "raw": "{{baseUrl}}/carts/add",
              "host": [
                "{{baseUrl}}"
              ],
              "path": [
                "carts",
                "add"
              ]
            }
          },
          "response": []
        }
      ]
    }
  ]
}